classgraphic/__init__.py
classgraphic/common.py
classgraphic/essential.py
classgraphic/table.py
classgraphic/template.py
classgraphic/viz.py
classgraphic-0.3.1.dist-info/AUTHORS.md
classgraphic-0.3.1.dist-info/LICENSE
classgraphic-0.3.1.dist-info/METADATA
classgraphic-0.3.1.dist-info/WHEEL
classgraphic-0.3.1.dist-info/top_level.txt
classgraphic-0.3.1.dist-info/RECORD
