Metadata-Version: 2.1
Name: classgraphic
Version: 0.3.1
Summary: Interactive classification diagnostic plots
Home-page: https://github.com/dionresearch/classgraphic
Author: Francois Dion
Author-email: fdion@dionresearch.com
License: MIT license
Keywords: classgraphic,classification,clustering,visualization,ml,machine learning,plotly,interactive
Classifier: Development Status :: 4 - Beta
Classifier: Intended Audience :: Developers
Classifier: License :: OSI Approved :: MIT License
Classifier: Natural Language :: English
Classifier: Programming Language :: Python :: 3
Classifier: Programming Language :: Python :: 3.8
Classifier: Programming Language :: Python :: 3.9
Classifier: Programming Language :: Python :: 3.10
Classifier: Programming Language :: Python :: 3.11
Requires-Python: >=3.6
License-File: LICENSE
License-File: AUTHORS.md
Requires-Dist: plotly (>=5.0)
Requires-Dist: scikit-learn
Requires-Dist: pandas
Requires-Dist: numpy
Requires-Dist: nbformat
